{
    "data_config": {
        "name": "PABP",
        "encoding": "one-hot",
        "attributes": []
    },
    "model_config": {
        "name": "MSATP",
        "dropout": 0,
        "enc_dim1": 1500,
        "enc_dim2": 1500,
        "z_dim": 32,
        "dec_dim1": 100,
        "dec_dim2": 500,
        "reconstruction_loss_weight": 1,
        "kl_div_weight": 100,
        "attr_decoding_loss_weight": 0
    },
    "train_config": {
        "seed": 42,
        "batch_size": 128,
        "learning_rate": 0.001,
        "num_epochs": 120
    }
}